timeblocks/__init__.py
timeblocks/apps.py
timeblocks/conf.py
timeblocks/constants.py
timeblocks/exceptions.py
timeblocks/admin/__init__.py
timeblocks/admin/series.py
timeblocks/admin/slot.py
timeblocks/migrations/0001_initial.py
timeblocks/migrations/__init__.py
timeblocks/models/__init__.py
timeblocks/models/querysets.py
timeblocks/models/series.py
timeblocks/models/slot.py
timeblocks/services/__init__.py
timeblocks/services/series_service.py
timeblocks/services/slot_generator.py
timeblocks/utils/timezone.py
timeblocks-0.1.3.dist-info/licenses/LICENSE
timeblocks-0.1.3.dist-info/METADATA
timeblocks-0.1.3.dist-info/WHEEL
timeblocks-0.1.3.dist-info/top_level.txt
timeblocks-0.1.3.dist-info/RECORD
