Metadata-Version: 2.4
Name: timeblocks
Version: 0.1.3
Summary: Reusable Django time block & recurrence engine.
Author-email: Rajat jog <rajatjog1294@gmail.com>
License: MIT
Requires-Python: >=3.8
License-File: LICENSE
Requires-Dist: Django>=3.2
Requires-Dist: python-dateutil>=2.8
Provides-Extra: dev
Requires-Dist: pytest; extra == "dev"
Requires-Dist: pytest-django; extra == "dev"
Dynamic: license-file
